[

{"date": "2015-01-01 21:21:00 +0200",
"categories": [],
"tags": [],
"title": "Kar ve Damlalar",
"url": "/2015/01/01/kar-ve-damlalar.html"},

{"date": "2015-01-01 14:02:00 +0200",
"categories": [],
"tags": [],
"title": 2015,
"url": "/2015/01/01/2015.html"},

{"date": "2014-12-21 22:24:00 +0200",
"categories": [],
"tags": [],
"title": "Giriş",
"url": "/2014/12/21/giris.html"},

{"date": "2014-12-18 00:51:00 +0200",
"categories": [],
"tags": [],
"title": "wow.js & animate.css",
"url": "/2014/12/18/wow-js-animate-css.html"},

{"date": "2014-12-16 23:15:00 +0200",
"categories": [],
"tags": [],
"title": "Spotify Year in Music 2014",
"url": "/2014/12/16/spotify-year-in-music-2014.html"},

{"date": "2014-11-20 00:00:00 +0200",
"categories": [],
"tags": [],
"title": "Tapatalk \"didn't receive 200 ok from remote server\" hatası",
"url": "/2014/11/20/tapatalk-didnt-receive-200-ok-from-remote-server-hatasi.html"},

{"date": "2014-11-15 17:54:00 +0200",
"categories": [],
"tags": [],
"title": "ASTR - Operate (The Chainsmokers Remix)",
"url": "/2014/11/15/astr-operate-the-chainsmokers-remix.html"},

{"date": "2014-10-09 20:24:00 +0300",
"categories": [],
"tags": [],
"title": "Ubuntu Mouse Tekerleği Hızı",
"url": "/2014/10/09/ubuntu-mouse-tekerlegi-hizi.html"},

{"date": "2014-10-04 10:45:00 +0300",
"categories": [],
"tags": [],
"title": "İyi Bayramlar",
"url": "/2014/10/04/iyi-bayramlar.html"},

{"date": "2014-07-21 22:16:00 +0300",
"categories": [],
"tags": [],
"title": "Bursaspor - Chikhura Sachkhere",
"url": "/2014/07/21/bursaspor-chikhura-sachkhere.html"},

{"date": "2014-07-14 11:05:00 +0300",
"categories": [],
"tags": [],
"title": "Summer",
"url": "/2014/07/14/summer.html"},

{"date": "2014-07-11 22:33:00 +0300",
"categories": [],
"tags": [],
"title": null,
"url": "/2014/07/11/10.html"},

{"date": "2014-05-28 21:09:00 +0300",
"categories": [],
"tags": [],
"title": "Alerji",
"url": "/2014/05/28/alerji.html"},

{"date": "2014-04-26 19:07:00 +0300",
"categories": [],
"tags": [],
"title": "Ubuntu Çevimiçi Hesaplar Problemi",
"url": "/2014/04/26/ubuntu-cevimici-hesaplar-problemi.html"},

{"date": "2014-04-13 13:24:00 +0300",
"categories": [],
"tags": [],
"title": 2048,
"url": "/2014/04/13/2048.html"},

{"date": "2014-04-13 12:45:00 +0300",
"categories": [],
"tags": [],
"title": "GitHub Reponuzu GitHub Subdomain Altında Yayınlama",
"url": "/2014/04/13/github-reponuzu-github-subdomain-altinda-yayinlama.html"},

{"date": "2014-01-06 15:44:00 +0200",
"categories": [],
"tags": [],
"title": "Pharrell Williams - Happy",
"url": "/2014/01/06/pharrell-williams-happy.html"},

{"date": "2013-12-29 13:46:00 +0200",
"categories": [],
"tags": [],
"title": "Composer Kurulumu",
"url": "/2013/12/29/composer-kurulumu.html"},

{"date": "2013-12-17 18:40:00 +0200",
"categories": ["commit","git","git commit","github","ide","phpstorm","phpstorm git","version control","web"],
"tags": [],
"title": "PhpStorm Git Entegrasyonu ve İlk Commit",
"url": "/commit/git/git%20commit/github/ide/phpstorm/phpstorm%20git/version%20control/web/2013/12/17/phpstorm-git-entegrasyonu-ve-ilk-commit.html"},

{"date": "2013-12-16 23:53:00 +0200",
"categories": ["blog","f1 2013","f1 2013 fullscreen","f12013"],
"tags": [],
"title": "F1 2013 Tam Ekran Problemi",
"url": "/blog/f1%202013/f1%202013%20fullscreen/f12013/2013/12/16/f1-2013-tam-ekran-problemi.html"},

{"date": "2013-12-15 22:10:00 +0200",
"categories": ["blog","fotoğraf","kar"],
"tags": [],
"title": "Kar",
"url": "/blog/foto%C4%9Fraf/kar/2013/12/15/kar.html"},

{"date": "2013-11-26 16:24:00 +0200",
"categories": ["blog","fotoğraf"],
"tags": [],
"title": "Pus",
"url": "/blog/foto%C4%9Fraf/2013/11/26/pus.html"},

{"date": "2013-11-14 23:39:00 +0200",
"categories": ["linux","sudo","vim"],
"tags": [],
"title": "5 Dakikada Vim Kullanımı",
"url": "/linux/sudo/vim/2013/11/14/5-dakikada-vim-kullanimi.html"},

{"date": "2013-11-11 21:22:00 +0200",
"categories": ["müzik"],
"tags": [],
"title": "Moguai - Champs",
"url": "/m%C3%BCzik/2013/11/11/moguai-champs.html"},

{"date": "2013-11-04 00:21:00 +0200",
"categories": ["chrome logger","debug","web"],
"tags": [],
"title": "Chrome Logger",
"url": "/chrome%20logger/debug/web/2013/11/04/chrome-logger.html"},

{"date": "2013-10-28 00:47:00 +0200",
"categories": ["arctic monkeys","avicii","blog","calvin harris","daft punk","empire of the sun","fedde le grand &amp; nicky romero","james murphy","little walter","muddy waters","müzik","pulp fiction","she &amp; him","the smiths"],
"tags": [],
"title": "Bu Aralar Neler Dinliyorum Vol.2",
"url": "/arctic%20monkeys/avicii/blog/calvin%20harris/daft%20punk/empire%20of%20the%20sun/fedde%20le%20grand%20&amp;%20nicky%20romero/james%20murphy/little%20walter/muddy%20waters/m%C3%BCzik/pulp%20fiction/she%20&amp;%20him/the%20smiths/2013/10/28/bu-aralar-neler-dinliyorum-vol-2.html"},

{"date": "2013-10-21 16:24:00 +0300",
"categories": ["müzik","sun don't shine"],
"tags": [],
"title": "Sun Don't Shine",
"url": "/m%C3%BCzik/sun%20don't%20shine/2013/10/21/sun-dont-shine.html"},

{"date": "2013-10-18 14:48:00 +0300",
"categories": ["afrojack","blog","rock the rock"],
"tags": [],
"title": "Rock the Rock",
"url": "/afrojack/blog/rock%20the%20rock/2013/10/18/rock-the-rock.html"},

{"date": "2013-10-14 20:23:00 +0300",
"categories": ["blog"],
"tags": [],
"title": "Bayramlarda Oluşan Alışveriş Çılgınlığı",
"url": "/blog/2013/10/14/bayramlarda-olusan-alisveris-cilginligi.html"},

{"date": "2013-10-14 16:08:00 +0300",
"categories": ["avm","blog","çalışan","mağaza","pişti","yanlış"],
"tags": [],
"title": "AVM'de Nasıl Mağaza Çalışanı Sanılırsınız?",
"url": "/avm/blog/%C3%A7al%C4%B1%C5%9Fan/ma%C4%9Faza/pi%C5%9Fti/yanl%C4%B1%C5%9F/2013/10/14/avmde-nasil-magaza-calisani-sanilirsiniz.html"},

{"date": "2013-10-05 10:44:00 +0300",
"categories": ["apple","apple ios7","blog","siri","sussan bennett"],
"tags": [],
"title": "Siri'nin Seslendiricisi Susan Bennett",
"url": "/apple/apple%20ios7/blog/siri/sussan%20bennett/2013/10/05/sirinin-seslendiricisi-susan-bennett.html"},

{"date": "2013-10-03 22:40:00 +0300",
"categories": ["admob","adsense","doubleclick","google","google adsense","google web designer","html5","html5 banner","web","web designer"],
"tags": [],
"title": "Google Web Designer",
"url": "/admob/adsense/doubleclick/google/google%20adsense/google%20web%20designer/html5/html5%20banner/web/web%20designer/2013/10/03/google-web-designer.html"},

{"date": "2013-09-25 22:46:00 +0300",
"categories": ["fotoğraf"],
"tags": [],
"title": "Yağmur Sonrası",
"url": "/foto%C4%9Fraf/2013/09/25/yagmur-sonrasi.html"},

{"date": "2013-09-12 08:35:00 +0300",
"categories": ["chill out","freddie mercury","müzik","queen"],
"tags": [],
"title": "Queen Chill Out",
"url": "/chill%20out/freddie%20mercury/m%C3%BCzik/queen/2013/09/12/queen-chill-out.html"},

{"date": "2013-09-11 20:32:00 +0300",
"categories": ["apple","blog","ios7","iphone","iphone 5c","iphone 5s"],
"tags": [],
"title": "iPhone 5C & iPhone 5S",
"url": "/apple/blog/ios7/iphone/iphone%205c/iphone%205s/2013/09/11/iphone-5c-iphone-5s.html"},

{"date": "2013-08-24 23:52:00 +0300",
"categories": ["apache","apache mod_rewrite","apache2","linux","mod_rewrite","sudo","web"],
"tags": [],
"title": "apache mod_rewrite aktif etmek",
"url": "/apache/apache%20mod_rewrite/apache2/linux/mod_rewrite/sudo/web/2013/08/24/apache-mod_rewrite-aktif-etmek.html"},

{"date": "2013-08-24 21:25:00 +0300",
"categories": ["apache2","git","linux","lubuntu","mysql","php","sublime text","sublime text install linux","vim"],
"tags": [],
"title": "Lubuntu Format Sonrası Yaptıklarım",
"url": "/apache2/git/linux/lubuntu/mysql/php/sublime%20text/sublime%20text%20install%20linux/vim/2013/08/24/lubuntu-format-sonrasi-yaptiklarim.html"},

{"date": "2013-08-04 20:01:00 +0300",
"categories": ["fotoğraf"],
"tags": [],
"title": "VW 1303",
"url": "/foto%C4%9Fraf/2013/08/04/vw-1303.html"},

{"date": "2013-08-03 21:35:00 +0300",
"categories": ["afrojack","müzik","ten feet tall","tomorrowland"],
"tags": [],
"title": "Afrojack - Ten Feet Tall",
"url": "/afrojack/m%C3%BCzik/ten%20feet%20tall/tomorrowland/2013/08/03/afrojack-ten-feet-tall.html"},

{"date": "2013-07-24 20:48:00 +0300",
"categories": ["fotoğraf"],
"tags": [],
"title": "İstanbul",
"url": "/foto%C4%9Fraf/2013/07/24/istanbul-1.html"},

{"date": "2013-07-19 19:08:00 +0300",
"categories": ["blog"],
"tags": [],
"title": "Rand vol2",
"url": "/blog/2013/07/19/rand-vol2.html"},

{"date": "2013-06-28 22:39:00 +0300",
"categories": ["müzik"],
"tags": [],
"title": null,
"url": "/m%C3%BCzik/2013/06/28/thicke_ef_bb_bf.html"},

{"date": "2013-06-16 22:22:00 +0300",
"categories": ["fotoğraf"],
"tags": [],
"title": "Mini Holiday",
"url": "/foto%C4%9Fraf/2013/06/16/mini-holiday.html"},

{"date": "2013-06-10 23:15:00 +0300",
"categories": ["apple ios7","blog","ios7"],
"tags": [],
"title": "iOS 7",
"url": "/apple%20ios7/blog/ios7/2013/06/10/ios-7.html"},

{"date": "2013-05-27 19:25:00 +0300",
"categories": ["axwell","discopolis","falling","müzik"],
"tags": [],
"title": "Falling",
"url": "/axwell/discopolis/falling/m%C3%BCzik/2013/05/27/falling.html"},

{"date": "2013-05-12 23:32:00 +0300",
"categories": ["fotoğraf"],
"tags": [],
"title": "Sevgi",
"url": "/foto%C4%9Fraf/2013/05/12/sevgi.html"},

{"date": "2013-04-19 19:38:00 +0300",
"categories": ["müzik"],
"tags": [],
"title": "Daft Punk - Get Lucky",
"url": "/m%C3%BCzik/2013/04/19/daft-punk-get-lucky.html"},

{"date": "2013-04-18 13:11:00 +0300",
"categories": ["müzik"],
"tags": [],
"title": "Bang Bang Bang",
"url": "/m%C3%BCzik/2013/04/18/bang-bang-bang.html"},

{"date": "2013-04-12 19:41:00 +0300",
"categories": ["linux","linux skype microsoft account problem","skype","skype linux","skype microsoft account problem"],
"tags": [],
"title": "Linux Sistemlerde Skype Microsoft Hesabı Sorunu",
"url": "/linux/linux%20skype%20microsoft%20account%20problem/skype/skype%20linux/skype%20microsoft%20account%20problem/2013/04/12/linux-sistemlerde-skype-microsoft-hesabi-sorunu.html"},

{"date": "2013-03-29 21:46:00 +0200",
"categories": ["fotoğraf"],
"tags": [],
"title": null,
"url": "/foto%C4%9Fraf/2013/03/29/53.html"},

{"date": "2013-03-26 13:30:00 +0200",
"categories": ["gif","google","google images","google images gif","web"],
"tags": [],
"title": "Google görsel aramarda gif filtrelemesi",
"url": "/gif/google/google%20images/google%20images%20gif/web/2013/03/26/google-gorsel-aramarda-gif-filtrelemesi.html"},

{"date": "2013-03-17 23:38:00 +0200",
"categories": ["fotoğraf"],
"tags": [],
"title": null,
"url": "/foto%C4%9Fraf/2013/03/17/55.html"},

{"date": "2013-03-17 00:25:00 +0200",
"categories": ["fotoğraf"],
"tags": [],
"title": null,
"url": "/foto%C4%9Fraf/2013/03/17/56.html"},

{"date": "2013-02-22 15:42:00 +0200",
"categories": ["blog","müzik"],
"tags": [],
"title": "Fault",
"url": "/blog/m%C3%BCzik/2013/02/22/fault.html"},

{"date": "2013-02-14 21:52:00 +0200",
"categories": ["linux","lubuntu","lubuntu wallpaper","lubuntu wallpaper directory"],
"tags": [],
"title": "Lubuntu default wallpaper directory",
"url": "/linux/lubuntu/lubuntu%20wallpaper/lubuntu%20wallpaper%20directory/2013/02/14/lubuntu-default-wallpaper-directory.html"},

{"date": "2013-02-03 13:31:00 +0200",
"categories": ["linux","lubuntu"],
"tags": [],
"title": "Lubuntu Maceraları Vol.1",
"url": "/linux/lubuntu/2013/02/03/lubuntu-maceralari-vol-1.html"},

{"date": "2013-02-02 00:12:00 +0200",
"categories": ["fotoğraf","sunset"],
"tags": [],
"title": "Sunset",
"url": "/foto%C4%9Fraf/sunset/2013/02/02/sunset.html"},

{"date": "2013-01-26 21:20:00 +0200",
"categories": ["fotoğraf","metro - xm - work - city - night"],
"tags": [],
"title": "Metro - Xm - Work - City - Night",
"url": "/foto%C4%9Fraf/metro%20-%20xm%20-%20work%20-%20city%20-%20night/2013/01/26/metro-xm-work-city-night.html"},

{"date": "2013-01-25 17:59:00 +0200",
"categories": ["fotoğraf"],
"tags": [],
"title": "Tiramisu",
"url": "/foto%C4%9Fraf/2013/01/25/tiramisu.html"},

{"date": "2013-01-25 00:14:00 +0200",
"categories": ["fotoğraf"],
"tags": [],
"title": null,
"url": "/foto%C4%9Fraf/2013/01/25/63.html"},

{"date": "2013-01-25 00:12:00 +0200",
"categories": ["fotoğraf"],
"tags": [],
"title": null,
"url": "/foto%C4%9Fraf/2013/01/25/64.html"},

{"date": "2013-01-24 01:42:00 +0200",
"categories": ["fotoğraf"],
"tags": [],
"title": null,
"url": "/foto%C4%9Fraf/2013/01/24/66.html"},

{"date": "2013-01-24 01:42:00 +0200",
"categories": ["fotoğraf"],
"tags": [],
"title": null,
"url": "/foto%C4%9Fraf/2013/01/24/65.html"},

{"date": "2013-01-24 00:48:00 +0200",
"categories": ["fotoğraf"],
"tags": [],
"title": null,
"url": "/foto%C4%9Fraf/2013/01/24/67.html"},

{"date": "2013-01-23 10:36:00 +0200",
"categories": ["fotoğraf","rain"],
"tags": [],
"title": null,
"url": "/foto%C4%9Fraf/rain/2013/01/23/rain.html"},

{"date": "2013-01-15 23:25:00 +0200",
"categories": ["facebook","facebook graph search","facebook graphsearch","graphsearch","web"],
"tags": [],
"title": "Facebook Graph Search",
"url": "/facebook/facebook%20graph%20search/facebook%20graphsearch/graphsearch/web/2013/01/15/facebook-graph-search.html"},

{"date": "2013-01-15 00:00:00 +0200",
"categories": [],
"tags": [],
"title": "Tenis Aktif Federer Comeze Ders Verdi",
"url": "/2013/01/15/tenis-aktif-federer-comeze-ders-verdi.html"},

{"date": "2013-01-14 01:01:00 +0200",
"categories": ["johnny depp","müzik","my valenine","natalie portman","paul mccartney"],
"tags": [],
"title": "Paul McCartney's - My Valentine",
"url": "/johnny%20depp/m%C3%BCzik/my%20valenine/natalie%20portman/paul%20mccartney/2013/01/14/paul-mccartneys-my-valentine.html"},

{"date": "2013-01-04 13:16:00 +0200",
"categories": ["blog"],
"tags": [],
"title": "Cinemagraph",
"url": "/blog/2013/01/04/cinemagraph.html"},

{"date": "2013-01-01 13:30:00 +0200",
"categories": ["müzik","who are you","yes man"],
"tags": [],
"title": "Who Are You",
"url": "/m%C3%BCzik/who%20are%20you/yes%20man/2013/01/01/who-are-you.html"},

{"date": "2012-12-31 21:57:00 +0200",
"categories": ["blog"],
"tags": [],
"title": "2012 Nasıl Geçti?",
"url": "/blog/2012/12/31/2012-nasil-gecti.html"},

{"date": "2012-12-27 00:23:00 +0200",
"categories": ["blog","keep calm","wake up"],
"tags": [],
"title": "Keep Calm and Wake Up",
"url": "/blog/keep%20calm/wake%20up/2012/12/27/keep-calm-and-wake-up.html"},

{"date": "2012-12-15 20:08:00 +0200",
"categories": ["blog","goblin shark"],
"tags": [],
"title": "Goblin Shark",
"url": "/blog/goblin%20shark/2012/12/15/goblin-shark.html"},

{"date": "2012-12-02 01:25:00 +0200",
"categories": ["25th hour","doyle's walk","edward norton","müzik","shazam"],
"tags": [],
"title": "Doyle's Walk",
"url": "/25th%20hour/doyle's%20walk/edward%20norton/m%C3%BCzik/shazam/2012/12/02/doyles-walk.html"},

{"date": "2012-11-30 21:45:00 +0200",
"categories": ["creata usb bootable","kubuntu","kubuntu usb","linux","linux bootable","lubuntu","lubuntu usb","releases.ubuntu","ubuntu","ubuntu usb","universal usb installer","usb bootable linux","xubuntu"],
"tags": [],
"title": "USB Üzerinden Linux Kurma",
"url": "/creata%20usb%20bootable/kubuntu/kubuntu%20usb/linux/linux%20bootable/lubuntu/lubuntu%20usb/releases.ubuntu/ubuntu/ubuntu%20usb/universal%20usb%20installer/usb%20bootable%20linux/xubuntu/2012/11/30/usb-uzerinden-linux-kurma.html"},

{"date": "2012-11-25 00:29:00 +0200",
"categories": ["badge","instagram","instagram badge","instagram profile","web"],
"tags": [],
"title": "Instagram Badges",
"url": "/badge/instagram/instagram%20badge/instagram%20profile/web/2012/11/25/instagram-badges.html"},

{"date": "2012-11-18 02:15:00 +0200",
"categories": ["beta","beta nedir","beta sürüm","beta sürüm nedir","beta sürümü","blog"],
"tags": [],
"title": "Beta nedir ne değildir?",
"url": "/beta/beta%20nedir/beta%20s%C3%BCr%C3%BCm/beta%20s%C3%BCr%C3%BCm%20nedir/beta%20s%C3%BCr%C3%BCm%C3%BC/blog/2012/11/18/beta-nedir-ne-degildir.html"},

{"date": "2012-11-13 23:25:00 +0200",
"categories": ["instagram","instagram profile","instagram profile page","new instagram profile page","web"],
"tags": [],
"title": "Instagram Profil Sayfaları",
"url": "/instagram/instagram%20profile/instagram%20profile%20page/new%20instagram%20profile%20page/web/2012/11/13/instagram-profil-sayfalari.html"},

{"date": "2012-10-21 20:50:00 +0300",
"categories": ["al green","blog","clash","elton john","guns n' roses","kiki dee","madonna","müzik","shawn mullins","startailor","sting","the cure","yavuz Çetin"],
"tags": [],
"title": "Bu Aralar Neler Dinliyorum Vol.1",
"url": "/al%20green/blog/clash/elton%20john/guns%20n'%20roses/kiki%20dee/madonna/m%C3%BCzik/shawn%20mullins/startailor/sting/the%20cure/yavuz%20%C3%87etin/2012/10/21/bu-aralar-neler-dinliyorum-vol-1.html"},

{"date": "2012-10-18 19:08:00 +0300",
"categories": ["blog"],
"tags": [],
"title": "Kendime Not",
"url": "/blog/2012/10/18/kendime-not.html"},

{"date": "2012-10-13 22:42:00 +0300",
"categories": ["fotoğraf"],
"tags": [],
"title": null,
"url": "/foto%C4%9Fraf/2012/10/13/84.html"},

{"date": "2012-09-25 23:07:00 +0300",
"categories": ["fotoğraf"],
"tags": [],
"title": null,
"url": "/foto%C4%9Fraf/2012/09/25/85.html"},

{"date": "2012-09-24 12:38:00 +0300",
"categories": ["film"],
"tags": [],
"title": "Stansfield",
"url": "/film/2012/09/24/stansfield.html"},

{"date": "2012-09-17 10:39:00 +0300",
"categories": ["müzik","starsailor - poor misguided fool"],
"tags": [],
"title": "Starsailor - Poor Misguided Fool",
"url": "/m%C3%BCzik/starsailor%20-%20poor%20misguided%20fool/2012/09/17/starsailor-poor-misguided-fool.html"},

{"date": "2012-09-09 11:37:00 +0300",
"categories": ["fotoğraf"],
"tags": [],
"title": null,
"url": "/foto%C4%9Fraf/2012/09/09/88.html"},

{"date": "2012-09-06 23:06:00 +0300",
"categories": ["lana del rey","müzik"],
"tags": [],
"title": "Lana Del Rey",
"url": "/lana%20del%20rey/m%C3%BCzik/2012/09/06/lana-del-rey.html"},

{"date": "2012-09-03 23:58:00 +0300",
"categories": ["fotoğraf"],
"tags": [],
"title": null,
"url": "/foto%C4%9Fraf/2012/09/03/90.html"},

{"date": "2012-09-03 23:52:00 +0300",
"categories": ["fotoğraf"],
"tags": [],
"title": null,
"url": "/foto%C4%9Fraf/2012/09/03/91.html"},

{"date": "2012-08-29 20:33:00 +0300",
"categories": ["blog"],
"tags": [],
"title": "Tesadüf",
"url": "/blog/2012/08/29/tesaduf.html"},

{"date": "2012-08-23 18:30:00 +0300",
"categories": ["fotoğraf"],
"tags": [],
"title": null,
"url": "/foto%C4%9Fraf/2012/08/23/93.html"},

{"date": "2012-08-21 00:39:00 +0300",
"categories": ["blog","fotoğraf"],
"tags": [],
"title": "Keyifli Yolculuk",
"url": "/blog/foto%C4%9Fraf/2012/08/21/keyifli-yolculuk.html"},

{"date": "2012-08-16 20:42:00 +0300",
"categories": ["blog"],
"tags": [],
"title": "Yorumlar ve Makale",
"url": "/blog/2012/08/16/yorumlar-ve-makale.html"},

{"date": "2012-08-13 23:48:00 +0300",
"categories": ["fotoğraf"],
"tags": [],
"title": "Bonanza",
"url": "/foto%C4%9Fraf/2012/08/13/bonanza.html"},

{"date": "2012-08-07 18:33:00 +0300",
"categories": ["lana del rey","müzik","national anthem"],
"tags": [],
"title": "Lana Del Rey - National Anthem",
"url": "/lana%20del%20rey/m%C3%BCzik/national%20anthem/2012/08/07/lana-del-rey-national-anthem.html"},

{"date": "2012-08-03 19:21:00 +0300",
"categories": ["lana del rey","müzik","video games"],
"tags": [],
"title": "Lana Del Rey - Video Games",
"url": "/lana%20del%20rey/m%C3%BCzik/video%20games/2012/08/03/lana-del-rey-video-games.html"},

{"date": "2012-07-11 14:04:00 +0300",
"categories": ["kodhane","kodhane.com","web"],
"tags": [],
"title": "Kodhane.com",
"url": "/kodhane/kodhane.com/web/2012/07/11/kodhane-com.html"},

{"date": "2012-07-05 20:18:00 +0300",
"categories": ["müzik"],
"tags": [],
"title": "Coldplay Violet Hill",
"url": "/m%C3%BCzik/2012/07/05/coldplay-violet-hill.html"},

{"date": "2012-05-22 21:16:00 +0300",
"categories": ["blog","oğlum bak git"],
"tags": [],
"title": "Oğlum Bak Git !",
"url": "/blog/o%C4%9Flum%20bak%20git/2012/05/22/oglum-bak-git.html"},

{"date": "2012-04-23 00:28:00 +0300",
"categories": ["blog","gs racing","gs xut tuggy","gs xut tuggy test"],
"tags": [],
"title": "Süper Performans",
"url": "/blog/gs%20racing/gs%20xut%20tuggy/gs%20xut%20tuggy%20test/2012/04/23/super-performans.html"},

{"date": "2012-04-20 18:29:00 +0300",
"categories": ["fotoğraf"],
"tags": [],
"title": null,
"url": "/foto%C4%9Fraf/2012/04/20/103.html"},

{"date": "2012-04-10 09:24:00 +0300",
"categories": ["fotoğraf","marty mcfly"],
"tags": [],
"title": "Marty McFly",
"url": "/foto%C4%9Fraf/marty%20mcfly/2012/04/10/marty-mcfly.html"},

{"date": "2012-04-09 23:09:00 +0300",
"categories": ["blog"],
"tags": [],
"title": "Neden Bloglamıyorum?",
"url": "/blog/2012/04/09/neden-bloglamiyorum.html"},

{"date": "2012-04-03 21:29:00 +0300",
"categories": ["blog","instagram","instagram android","instagram for android"],
"tags": [],
"title": "Beklenen Uygulama Geldi",
"url": "/blog/instagram/instagram%20android/instagram%20for%20android/2012/04/03/beklenen-uygulama-geldi.html"},

{"date": "2012-03-28 23:51:00 +0300",
"categories": ["fotoğraf"],
"tags": [],
"title": null,
"url": "/foto%C4%9Fraf/2012/03/28/107.html"},

{"date": "2012-03-14 20:31:00 +0200",
"categories": ["blog","cad vs helicopter","kedi ve helikopter"],
"tags": [],
"title": "Kedi vs Helikopter",
"url": "/blog/cad%20vs%20helicopter/kedi%20ve%20helikopter/2012/03/14/kedi-vs-helikopter.html"},

{"date": "2012-03-08 23:20:00 +0200",
"categories": ["blog","üniversite ders notları","üniversite ders notu","üniversite notları","web"],
"tags": [],
"title": "Üniversite Ders Notları",
"url": "/blog/%C3%BCniversite%20ders%20notlar%C4%B1/%C3%BCniversite%20ders%20notu/%C3%BCniversite%20notlar%C4%B1/web/2012/03/08/universite-ders-notlari.html"},

{"date": "2012-02-28 21:13:00 +0200",
"categories": ["blog","dirt nitro challenge truck final","nitro"],
"tags": [],
"title": "Dirt Nitro Challenge Truck Final 2012",
"url": "/blog/dirt%20nitro%20challenge%20truck%20final/nitro/2012/02/28/dirt-nitro-challenge-truck-final-2012.html"},

{"date": "2012-02-23 16:51:00 +0200",
"categories": ["fotoğraf"],
"tags": [],
"title": null,
"url": "/foto%C4%9Fraf/2012/02/23/111.html"},

{"date": "2012-02-17 00:04:00 +0200",
"categories": ["php","php hava durumu","php türkiye hava durumları","web"],
"tags": [],
"title": "Tüm Şehirlerin Hava Durumu - PHP",
"url": "/php/php%20hava%20durumu/php%20t%C3%BCrkiye%20hava%20durumlar%C4%B1/web/2012/02/17/tum-sehirlerin-hava-durumu-php.html"},

{"date": "2012-02-08 20:41:00 +0200",
"categories": ["blog","gs racing","gs xut tuggy","gs xut tuggy test","nitro"],
"tags": [],
"title": "Gs Xut Truggy Test",
"url": "/blog/gs%20racing/gs%20xut%20tuggy/gs%20xut%20tuggy%20test/nitro/2012/02/08/gs-xut-truggy-test.html"},

{"date": "2012-02-03 23:31:00 +0200",
"categories": ["blog","web"],
"tags": [],
"title": "Web Projeleri",
"url": "/blog/web/2012/02/03/web-projeleri.html"},

{"date": "2012-01-28 22:50:00 +0200",
"categories": ["blog","gs racing","gs xut tuggy","nitro"],
"tags": [],
"title": "Gs Xut Truggy",
"url": "/blog/gs%20racing/gs%20xut%20tuggy/nitro/2012/01/28/gs-xut-truggy.html"},

{"date": "2012-01-25 23:18:00 +0200",
"categories": ["blog"],
"tags": [],
"title": "Yakında Başlıyoruz",
"url": "/blog/2012/01/25/yakinda-basliyoruz.html"},

{"date": "2012-01-24 12:59:00 +0200",
"categories": ["fotoğraf"],
"tags": [],
"title": "İbo",
"url": "/foto%C4%9Fraf/2012/01/24/ibo.html"},

{"date": "2012-01-24 00:25:00 +0200",
"categories": ["blog"],
"tags": [],
"title": "Merhabalar",
"url": "/blog/2012/01/24/merhabalar.html"},

false]
